[
   {"text":"2017"},
   {"datetime":"2017-02-07","href":"html/interview2","text":"新致软件面试","original":"true"},
   {"datetime":"2017-02-06","href":"html/http","text":"关于http","original":"false"},
   {"datetime":"2017-01-15","href":"html/ioIntroduce","text":"io流介绍","original":"true"},
   {"datetime":"2017-01-11","href":"html/concurrent/volatile","text":"我对volatile的理解","original":"true"},
   {"datetime":"2017-01-04","href":"html/doublecheck","text":"双重检查","original":"true"},
   {"datetime":"2017-01-03","href":"html/negativepositivelock","text":"悲观锁和乐观锁","original":"true"},
   {"text":"2016"},
   {"datetime":"2016-12-27","href":"html/interview","text":"面试题总结","original":"true"},
   {"datetime":"2016-12-23","href":"html/identifyingCode","text":"验证码的新思路","original":"true"},
   {"datetime":"2016-12-20","href":"html/springboot/problems","text":"springboot的几个问题","original":"false"}
]